scihence/__init__.py
scihence/ai/__init__.py
scihence/ai/_data.py
scihence/ai/_io.py
scihence/ai/evaluation/__init__.py
scihence/ai/evaluation/_classification.py
scihence/ai/evaluation/_regression.py
scihence/ai/evaluation/_scoring_functions.py
scihence/ai/experiment_tracking/__init__.py
scihence/ai/experiment_tracking/_mlflow.py
scihence/ai/models/__init__.py
scihence/ai/models/_generic.py
scihence/ai/models/_sequential_torch.py
scihence/ai/models/_sklearn_logistic_regression.py
scihence/ai/models/_sklearn_ridge_regression.py
scihence/ai/models/_torch.py
scihence/ai/models/_torch_linear_regression.py
scihence/ai/models/_torch_logistic_regression.py
scihence/ai/models/_utils.py
scihence/ai/models/_xgboost.py
scihence/ai/models/processors/__init__.py
scihence/ai/models/processors/_base.py
scihence/ai/models/processors/_sub_div.py
scihence/ai/pipelines/__init__.py
scihence/ai/pipelines/supervised/__init__.py
scihence/ai/pipelines/supervised/_check.py
scihence/ai/pipelines/supervised/_main.py
scihence/ai/pipelines/supervised/_split.py
scihence/utils/__init__.py
scihence/utils/_dict.py
scihence/utils/_functools.py
scihence/utils/_math.py
scihence/utils/_reproduce.py
scihence/visualize/__init__.py
scihence/visualize/_style.py
scihence/visualize/fonts/noto/sans/NotoSans-Black.ttf
scihence/visualize/fonts/noto/sans/NotoSans-BlackItalic.ttf
scihence/visualize/fonts/noto/sans/NotoSans-Bold.ttf
scihence/visualize/fonts/noto/sans/NotoSans-BoldItalic.ttf
scihence/visualize/fonts/noto/sans/NotoSans-ExtraBold.ttf
scihence/visualize/fonts/noto/sans/NotoSans-ExtraBoldItalic.ttf
scihence/visualize/fonts/noto/sans/NotoSans-ExtraLight.ttf
scihence/visualize/fonts/noto/sans/NotoSans-ExtraLightItalic.ttf
scihence/visualize/fonts/noto/sans/NotoSans-Italic.ttf
scihence/visualize/fonts/noto/sans/NotoSans-Light.ttf
scihence/visualize/fonts/noto/sans/NotoSans-LightItalic.ttf
scihence/visualize/fonts/noto/sans/NotoSans-Medium.ttf
scihence/visualize/fonts/noto/sans/NotoSans-MediumItalic.ttf
scihence-0.0.1.dist-info/LICENSE
scihence-0.0.1.dist-info/METADATA
scihence-0.0.1.dist-info/WHEEL
scihence-0.0.1.dist-info/top_level.txt
scihence-0.0.1.dist-info/RECORD
