Metadata-Version: 2.1
Name: scihence
Version: 0.0.1
Summary: Henry's tools in Python.
Home-page: https://gitlab.com/HennersBro98/scihence
Author: Henry Broomfield
License: (C) Henry Broomfield
Requires-Python: >=3.11.0,<3.12
License-File: LICENSE
Requires-Dist: matplotlib <4,>=3.5.0
Requires-Dist: mlflow <3,>=2.1.1
Requires-Dist: numpy <2,>=1.23.0
Requires-Dist: pandas <3,>=2.0.0
Requires-Dist: Pillow <11,>=10.0.0
Requires-Dist: plotly <8,>=5.0.0
Requires-Dist: seaborn <1,>=0.12.0
Requires-Dist: xgboost <2,>=1.7.0
Provides-Extra: build
Requires-Dist: build ; extra == 'build'
Requires-Dist: tox ; extra == 'build'
Provides-Extra: check
Requires-Dist: pre-commit ; extra == 'check'
Requires-Dist: tox ; extra == 'check'
Provides-Extra: dev
Requires-Dist: build ; extra == 'dev'
Requires-Dist: tox ; extra == 'dev'
Requires-Dist: pre-commit ; extra == 'dev'
Requires-Dist: furo ; extra == 'dev'
Requires-Dist: sphinx ; extra == 'dev'
Requires-Dist: ruff ; extra == 'dev'
Requires-Dist: twine ; extra == 'dev'
Requires-Dist: junit2html ; extra == 'dev'
Requires-Dist: pytest ; extra == 'dev'
Requires-Dist: pytest-cov ; extra == 'dev'
Provides-Extra: docs
Requires-Dist: furo ; extra == 'docs'
Requires-Dist: pre-commit ; extra == 'docs'
Requires-Dist: sphinx ; extra == 'docs'
Requires-Dist: tox ; extra == 'docs'
Provides-Extra: lint
Requires-Dist: ruff ; extra == 'lint'
Requires-Dist: tox ; extra == 'lint'
Provides-Extra: pub
Requires-Dist: twine ; extra == 'pub'
Provides-Extra: test
Requires-Dist: junit2html ; extra == 'test'
Requires-Dist: pytest ; extra == 'test'
Requires-Dist: pytest-cov ; extra == 'test'
Requires-Dist: tox ; extra == 'test'
